pyKamibot/__init__.py
pyKamibot/kamibot.py
pyKamibot/version.py
pyKamibot-0.15.dist-info/LICENSE
pyKamibot-0.15.dist-info/METADATA
pyKamibot-0.15.dist-info/WHEEL
pyKamibot-0.15.dist-info/top_level.txt
pyKamibot-0.15.dist-info/RECORD
