Metadata-Version: 2.1
Name: pyKamibot
Version: 0.15
Summary: A Python Library For Kamibot
Home-page: UNKNOWN
Author: moyalab
Author-email: iammoyalab@gmail.com
License: UNKNOWN
Keywords: Kamibot,Robot
Platform: UNKNOWN
Classifier: Operating System :: Microsoft :: Windows
Classifier: Programming Language :: Python :: 3.7
Classifier: Programming Language :: Python :: 3.8
Classifier: Programming Language :: Python :: 3.9
Classifier: License :: OSI Approved :: GNU Lesser General Public License v2 or later (LGPLv2+)
Requires-Python: >=3.7
Requires-Dist: pyserial (==3.5)
